{
  "name": "Millie Massey",
  "age": 32,
  "address": {
    "street": "Kene Boulevard",
    "city": "Upojemeg",
    "state": "OR",
    "zip": "45958"
  },
  "contact": {
    "phone": "(570) 500-9198",
    "servicePhone": "800744664"
  },
  "birthday": "2005-01-04T08:39:59.335Z",
  "ip": "107.104.18.223",
  "foo": "bar",
  "profile": {
    "about": "Cadva vul iju pow capbufe mubvu fi eb wo ku vohad dihuk fab. Ucutije la fonjufir muf kar waamoru seteb orluj sod togaewi vot zodudo cakcucwon owawozus tob we kiaznor. Gij jalam gadnehwij vogulo suud netifo viru bak ligwogceg jomodeelu jomusfes alaji. Vupac tucbov huce be revidi nujucisa levri heele dakumuje rihbeklak iwetu wevim kalal pafu. Hep verejube zorkat hezaut hahi kuwkaulo damiiku zual ad kopup kas otlurud etu ihipovsu.",
    "bio": "Vujo fapom ana tapamuz ekuovoac rahpul ju on omta vit va funnem fig lo hube rafhuti adaffi. Fecufo tefuz bokohfa hifmi ev zep soke fajurmak reva nefavi op ic gotiane rim. Ha lomcit saba fok abwuca jej votif na isasu rujzac po je hones ubogivi pigu omsemer aje. Cipsomga hagzufgeg uveju zuvga ogwi zi vi lejmief tile mermuttu itisiva ehe. Lapofi rasa libab kepino sam hikguup niope epwuzo wi fa cirratfa panamgac civvubja tecuhi jelsokdu gebmu. Pe nubopfu vojgol goziv kiskuw ewose kiamawi fibak upu nomluwam bogazhud gon icliwa."
  },
  "apiKey": "5542d79d69f1a3538b3d20cf8dd0392c54acac526ed239fed48694baf8272788",
  "currency": {
    "code": "SHP",
    "name": "Saint Helena Pound"
  }
}