{
  "name": "Bettie Hogan",
  "age": 64,
  "address": {
    "street": "Siazo Glen",
    "city": "Wovadud",
    "state": "AL",
    "zip": "11210"
  },
  "contact": {
    "phone": "(846) 683-5395",
    "servicePhone": "800439733"
  },
  "birthday": "1995-05-19T02:18:37.559Z",
  "ip": "128.203.222.75",
  "foo": "bar",
  "profile": {
    "about": "Julpuca tubciseh ozjob tisumik zuzukeve ogetmiw ceg walpefcus hozhasvi bikupawo ufzel ahpefbu dodi ku bihan sote. Oreud nocakiova laplijvo gecah kel abe tiganav ozijamup cupeehu vozuibu garsucina ja bagenu vu zi enibe vo. Pupapu paf sunalu rokik do lefugoem polej mewa esesaz vurku coes wojku zimkombij inirapip ovesi raczup forobbo. Paliwin abtuzgir he ric lopduw us nage fi wu fud gizceh ecoosin. Zo dud sehut da udmac rewhef widup riz zim zibeguun zavbi nerdama juasehe vilwuha sap. Vani jubop seturalaz fariido gonzefeka veeprog lizheru kezhueme inicomka filjemsin te lozrar sejum abmobro pocruhgav. Vi usa tojronsa jicmalge omadu powokuf kigvir miril da tidmu fogcus ije.",
    "bio": "Resi jip odonahubo hauseseh tuwoma lu vis ga devedi vesok lu jiel tacke wojihe nafse bomke lefo cibit. Zegan cujsinnir mocungi wabigab kaka zad ufo asusug bal si sokraj pallo zeok ogo ojohinar wu ciral tiz. Kap guwudlel wihivhas jon damsiltat cagose feta lunbendo ro tuca evkapes absad sowsi felwupik. Ki begzajid gejat bojoboja epouto guimenep gi pemfec pathu otdu julku ji kocdaw peotu bundale. Jir sabwi wub nel raj gibeh edacce bisjiw du va wamus lazih rakiczu mizeh lurzi izte. Loume umgo lo roviguzi ekuwi remnuh gizej do za wip iw ben bilarwef viibned utasbe jimlazli apegeefe. Pif jib ha ol nug hu atcuubi fi wekufpod avmaca ulwiriba jitvi voruvov orocidsa."
  },
  "apiKey": "2670e6bd31d8f589503ac983efd7383809d9c9a3da5f85cff3316697bb5310ed",
  "currency": {
    "code": "ARS",
    "name": "Argentina Peso"
  }
}